centra_py_client/__init__.py
centra_py_client/centra_py_client.py
centra_py_client/centra_session.py
centra_py_client/exceptions.py
centra_py_client-0.5.0.dist-info/LICENSE
centra_py_client-0.5.0.dist-info/METADATA
centra_py_client-0.5.0.dist-info/WHEEL
centra_py_client-0.5.0.dist-info/top_level.txt
centra_py_client-0.5.0.dist-info/RECORD
