Metadata-Version: 2.1
Name: centra-py-client
Version: 0.5.0
Summary: Python client for Centra API access.
Home-page: https://github.com/guardicode/centra-py-client
Author: Yonatan Golan
Author-email: yonatan.golan@guardicore.com
License: GNU General Public License v3
Keywords: centra_py_client
Platform: UNKNOWN
Classifier: Development Status :: 2 - Pre-Alpha
Classifier: Intended Audience :: Developers
Classifier: License :: OSI Approved :: GNU General Public License v3 (GPLv3)
Classifier: Natural Language :: English
Classifier: Programming Language :: Python :: 3
Classifier: Programming Language :: Python :: 3.7
Classifier: Programming Language :: Python :: 3.8
Requires-Python: >=3.7
Requires-Dist: requests
